{"updated": "16.07.2026 11:42", "assets": {"NVDA": {"name": "NVIDIA Corporation", "group": "Chips/AI", "price_eur": 185.3213}, "AMD": {"name": "Advanced Micro Devices, Inc.", "group": "Chips/AI", "price_eur": 461.463}, "TSM": {"name": "Taiwan Semiconductor Manufactur", "group": "Chips/AI", "price_eur": 365.8285}, "ASML": {"name": "ASML Holding N.V. - New York Re", "group": "Chips/AI", "price_eur": 1583.097}, "AVGO": {"name": "Broadcom Inc.", "group": "Chips/AI", "price_eur": 343.8516}, "SMCI": {"name": "Super Micro Computer, Inc.", "group": "Chips/AI", "price_eur": 23.4508}, "VRT": {"name": "Vertiv Holdings, LLC", "group": "Datacenter", "price_eur": 265.6155}, "EQIX": {"name": "Equinix, Inc.", "group": "Datacenter", "price_eur": 891.8095}, "CLS": {"name": "Celestica, Inc.", "group": "Datacenter", "price_eur": 291.9529}, "DELL": {"name": "Dell Technologies Inc.", "group": "Datacenter", "price_eur": 359.8982}, "MSFT": {"name": "Microsoft Corporation", "group": "Big Tech", "price_eur": 345.0289}, "GOOGL": {"name": "Alphabet Inc.", "group": "Big Tech", "price_eur": 323.4794}, "AMZN": {"name": "Amazon.com, Inc.", "group": "Big Tech", "price_eur": 222.3506}, "META": {"name": "Meta Platforms, Inc.", "group": "Big Tech", "price_eur": 594.1705}, "AAPL": {"name": "Apple Inc.", "group": "Big Tech", "price_eur": 285.6128}, "TSLA": {"name": "Tesla, Inc.", "group": "Big Tech", "price_eur": 344.0086}, "PLTR": {"name": "Palantir Technologies Inc.", "group": "Software", "price_eur": 116.6521}, "CRWD": {"name": "CrowdStrike Holdings, Inc.", "group": "Software", "price_eur": 180.3241}, "NET": {"name": "Cloudflare, Inc.", "group": "Software", "price_eur": 238.1182}, "SAP.DE": {"name": "SAP SE                        I", "group": "Europa", "price_eur": 137.36}, "SIE.DE": {"name": "SIEMENS AG                    N", "group": "Europa", "price_eur": 270.7}, "ALV.DE": {"name": "Allianz SE                    v", "group": "Europa", "price_eur": 415.9}, "RHM.DE": {"name": "RHEINMETALL AG                I", "group": "Europa", "price_eur": 966.4}, "AIR.PA": {"name": "AIRBUS SE", "group": "Europa", "price_eur": 195.38}, "MC.PA": {"name": "LVMH", "group": "Europa", "price_eur": 492.75}, "GE": {"name": "GE Aerospace", "group": "Industrie", "price_eur": 314.2612}, "CAT": {"name": "Caterpillar, Inc.", "group": "Industrie", "price_eur": 797.361}, "FCX": {"name": "Freeport-McMoRan, Inc.", "group": "Rohstoffe", "price_eur": 53.1719}, "XOM": {"name": "ExxonMobil Holdings Corporation", "group": "Energie", "price_eur": 126.0272}, "LMT": {"name": "Lockheed Martin Corporation", "group": "Defense", "price_eur": 448.6606}, "EUNL.DE": {"name": "iShares Core MSCI World", "group": "ETF Welt", "price_eur": 125.98}, "VWCE.DE": {"name": "Vanguard FTSE All-World", "group": "ETF Welt", "price_eur": 165.26}, "SXR8.DE": {"name": "iShares Core S&P 500", "group": "ETF USA", "price_eur": 711.22}, "SXRV.DE": {"name": "iShares Nasdaq 100", "group": "ETF USA", "price_eur": 1475.2}, "IS3N.DE": {"name": "iShares MSCI EM IMI", "group": "ETF Schwellenländer", "price_eur": 46.38}, "EXSA.DE": {"name": "iShares STOXX Europe 600", "group": "ETF Europa", "price_eur": 63.82}, "XAIX.DE": {"name": "Xtrackers AI & Big Data", "group": "ETF Thema", "price_eur": 198.64}, "VVSM.DE": {"name": "VanEck Semiconductor", "group": "ETF Thema", "price_eur": 95.44}, "bitcoin": {"name": "Bitcoin", "group": "Krypto", "price_eur": 55867.0}, "ethereum": {"name": "Ethereum", "group": "Krypto", "price_eur": 1642.38}, "solana": {"name": "Solana", "group": "Krypto", "price_eur": 66.34}, "ripple": {"name": "XRP", "group": "Krypto", "price_eur": 0.964286}, "cardano": {"name": "Cardano", "group": "Krypto", "price_eur": 0.141263}, "dogecoin": {"name": "Dogecoin", "group": "Krypto", "price_eur": 0.063717}, "polkadot": {"name": "Polkadot", "group": "Krypto", "price_eur": 0.729338}, "chainlink": {"name": "Chainlink", "group": "Krypto", "price_eur": 7.34}, "avalanche-2": {"name": "Avalanche", "group": "Krypto", "price_eur": 5.75}, "litecoin": {"name": "Litecoin", "group": "Krypto", "price_eur": 38.95}}}