{"updated": "07.07.2026 18:04", "assets": {"NVDA": {"name": "NVIDIA Corporation", "group": "Chips/AI", "price_eur": 170.9245}, "AMD": {"name": "Advanced Micro Devices, Inc.", "group": "Chips/AI", "price_eur": 453.293}, "TSM": {"name": "Taiwan Semiconductor Manufactur", "group": "Chips/AI", "price_eur": 380.0778}, "ASML": {"name": "ASML Holding N.V. - New York Re", "group": "Chips/AI", "price_eur": 1525.0106}, "AVGO": {"name": "Broadcom Inc.", "group": "Chips/AI", "price_eur": 324.2158}, "SMCI": {"name": "Super Micro Computer, Inc.", "group": "Chips/AI", "price_eur": 22.8182}, "VRT": {"name": "Vertiv Holdings, LLC", "group": "Datacenter", "price_eur": 260.7886}, "EQIX": {"name": "Equinix, Inc.", "group": "Datacenter", "price_eur": 892.602}, "CLS": {"name": "Celestica, Inc.", "group": "Datacenter", "price_eur": 298.3303}, "DELL": {"name": "Dell Technologies Inc.", "group": "Datacenter", "price_eur": 363.464}, "MSFT": {"name": "Microsoft Corporation", "group": "Big Tech", "price_eur": 344.3081}, "GOOGL": {"name": "Alphabet Inc.", "group": "Big Tech", "price_eur": 322.2337}, "AMZN": {"name": "Amazon.com, Inc.", "group": "Big Tech", "price_eur": 213.5857}, "META": {"name": "Meta Platforms, Inc.", "group": "Big Tech", "price_eur": 528.9367}, "AAPL": {"name": "Apple Inc.", "group": "Big Tech", "price_eur": 275.0614}, "TSLA": {"name": "Tesla, Inc.", "group": "Big Tech", "price_eur": 356.3845}, "PLTR": {"name": "Palantir Technologies Inc.", "group": "Software", "price_eur": 118.4885}, "CRWD": {"name": "CrowdStrike Holdings, Inc.", "group": "Software", "price_eur": 173.1035}, "NET": {"name": "Cloudflare, Inc.", "group": "Software", "price_eur": 230.7289}, "SAP.DE": {"name": "SAP SE                        I", "group": "Europa", "price_eur": 143.9}, "SIE.DE": {"name": "SIEMENS AG                    N", "group": "Europa", "price_eur": 269.6}, "ALV.DE": {"name": "Allianz SE                    v", "group": "Europa", "price_eur": 422.8}, "RHM.DE": {"name": "RHEINMETALL AG                I", "group": "Europa", "price_eur": 1111.6}, "AIR.PA": {"name": "AIRBUS SE", "group": "Europa", "price_eur": 203.95}, "MC.PA": {"name": "LVMH", "group": "Europa", "price_eur": 495.8}, "GE": {"name": "GE Aerospace", "group": "Industrie", "price_eur": 320.8117}, "CAT": {"name": "Caterpillar, Inc.", "group": "Industrie", "price_eur": 801.2451}, "FCX": {"name": "Freeport-McMoRan, Inc.", "group": "Rohstoffe", "price_eur": 52.2697}, "XOM": {"name": "ExxonMobil Holdings Corporation", "group": "Energie", "price_eur": 122.5753}, "LMT": {"name": "Lockheed Martin Corporation", "group": "Defense", "price_eur": 470.0731}, "EUNL.DE": {"name": "iShares Core MSCI World", "group": "ETF Welt", "price_eur": 125.4}, "VWCE.DE": {"name": "Vanguard FTSE All-World", "group": "ETF Welt", "price_eur": 164.82}, "SXR8.DE": {"name": "iShares Core S&P 500", "group": "ETF USA", "price_eur": 705.44}, "SXRV.DE": {"name": "iShares Nasdaq 100", "group": "ETF USA", "price_eur": 1462.0}, "IS3N.DE": {"name": "iShares MSCI EM IMI", "group": "ETF Schwellenländer", "price_eur": 46.813}, "EXSA.DE": {"name": "iShares STOXX Europe 600", "group": "ETF Europa", "price_eur": 64.45}, "XAIX.DE": {"name": "Xtrackers AI & Big Data", "group": "ETF Thema", "price_eur": 200.65}, "VVSM.DE": {"name": "VanEck Semiconductor", "group": "ETF Thema", "price_eur": 94.34}, "bitcoin": {"name": "Bitcoin", "group": "Krypto", "price_eur": 55929.0}, "ethereum": {"name": "Ethereum", "group": "Krypto", "price_eur": 1571.25}, "solana": {"name": "Solana", "group": "Krypto", "price_eur": 71.79}, "ripple": {"name": "XRP", "group": "Krypto", "price_eur": 0.988261}, "cardano": {"name": "Cardano", "group": "Krypto", "price_eur": 0.155255}, "dogecoin": {"name": "Dogecoin", "group": "Krypto", "price_eur": 0.065784}, "polkadot": {"name": "Polkadot", "group": "Krypto", "price_eur": 0.764251}, "chainlink": {"name": "Chainlink", "group": "Krypto", "price_eur": 7.0}, "avalanche-2": {"name": "Avalanche", "group": "Krypto", "price_eur": 5.92}, "litecoin": {"name": "Litecoin", "group": "Krypto", "price_eur": 38.98}}}